convml_tt/.flake8
convml_tt/__init__.py
convml_tt/backbones.py
convml_tt/pipeline.py
convml_tt/system.py
convml_tt/trainer.py
convml_tt/trainer_logging.py
convml_tt/trainer_onecycle.py
convml_tt/architectures/__init__.py
convml_tt/architectures/triplet_trainer.py
convml_tt/data/__init__.py
convml_tt/data/common.py
convml_tt/data/dataset.py
convml_tt/data/examples.py
convml_tt/data/transforms.py
convml_tt/data/triplets.py
convml_tt/external/__init__.py
convml_tt/external/extract_model.py
convml_tt/external/fastai.py
convml_tt/external/fastai1_weights_loader.py
convml_tt/external/nn_layers.py
convml_tt/interpretation/__init__.py
convml_tt/interpretation/embedding_transforms.py
convml_tt/interpretation/tensorboard_projector.py
convml_tt/interpretation/plots/__init__.py
convml_tt/interpretation/plots/annotated_scatter_plot.py
convml_tt/interpretation/plots/dendrogram.py
convml_tt/interpretation/plots/grid_overview.py
convml_tt/interpretation/plots/isomap2d.py
convml_tt/interpretation/plots/manifold2d.py
convml_tt/interpretation/plots/utils.py
convml_tt/interpretation/plots/mpl_autopos_annotation/__init__.py
convml_tt/interpretation/plots/mpl_autopos_annotation/convex_hull.py
convml_tt/interpretation/plots/mpl_autopos_annotation/forces.py
convml_tt/interpretation/rectpred/__init__.py
convml_tt/interpretation/rectpred/data.py
convml_tt/interpretation/rectpred/flow.py
convml_tt/interpretation/rectpred/plot.py
convml_tt/interpretation/rectpred/sample.py
convml_tt/interpretation/rectpred/viz.py
convml_tt/interpretation/rectpred/flow/__init__.py
convml_tt/interpretation/rectpred/flow/calc.py
convml_tt/interpretation/rectpred/flow/plot.py
convml_tt/interpretation/rectpred/pipeline/__init__.py
convml_tt/interpretation/rectpred/pipeline/data.py
convml_tt/interpretation/rectpred/pipeline/flow.py
convml_tt/interpretation/rectpred/pipeline/plot.py
convml_tt/interpretation/rectpred/pipeline/transforms.py
convml_tt/interpretation/trajectories/__init__.py
convml_tt-0.14.2.dist-info/METADATA
convml_tt-0.14.2.dist-info/WHEEL
convml_tt-0.14.2.dist-info/top_level.txt
convml_tt-0.14.2.dist-info/RECORD
