Metadata-Version: 2.1
Name: convml-tt
Version: 0.14.2
Summary: Neural Network based study of convective organisation
Home-page: https://github.com/convml/convml_tt
Author: Leif denby
Author-email: l.c.denby@leeds.ac.uk
License: Apache
Classifier: Development Status :: 5 - Production/Stable
Classifier: License :: OSI Approved :: Apache Software License
Classifier: Operating System :: OS Independent
Classifier: Intended Audience :: Science/Research
Classifier: Programming Language :: Python
Classifier: Programming Language :: Python :: 3
Classifier: Programming Language :: Python :: 3.8
Classifier: Programming Language :: Python :: 3.9
Classifier: Topic :: Scientific/Engineering
Requires-Python: >=3.7
Requires-Dist: xarray
Requires-Dist: netCDF4
Requires-Dist: matplotlib
Requires-Dist: pytorch-lightning <2.0.0,>=1.2.0
Requires-Dist: kornia >=0.5.0
Requires-Dist: scikit-learn
Requires-Dist: seaborn
Requires-Dist: parse
Requires-Dist: jupyter
Requires-Dist: scikit-image
Requires-Dist: antialiased-cnns >=0.3
Requires-Dist: torchvision >=0.4.0
Requires-Dist: semver
Requires-Dist: statsmodels
Requires-Dist: numpy <2.0.0
Provides-Extra: dev
Requires-Dist: pytest ; extra == 'dev'
Requires-Dist: nbval ; extra == 'dev'
Requires-Dist: pre-commit ; extra == 'dev'
Requires-Dist: ipython ; extra == 'dev'
Provides-Extra: pipeline
Requires-Dist: luigi ; extra == 'pipeline'
Provides-Extra: sattiles
Requires-Dist: luigi ; extra == 'sattiles'
Requires-Dist: cartopy ; extra == 'sattiles'
Requires-Dist: satpy ; extra == 'sattiles'
Requires-Dist: esmpy ; extra == 'sattiles'
Requires-Dist: xesmf ; extra == 'sattiles'
Requires-Dist: convml-data >=0.2.0 ; extra == 'sattiles'
Provides-Extra: test
Requires-Dist: pytest ; extra == 'test'
Requires-Dist: nbval ; extra == 'test'
